{
    "id": 10565740,
    "name": "Bloodbath",
    "author": "Riot",
    "creators": ["Riot & More"],
    "verifier": "BoldStep",
    "verification": "https://www.youtube.com/watch?v=rO0iTvZPtwY",
    "percentToQualify": 100,
    "password": "Free Copy",
    "records": [
        {
            "user": "Extravagon",
            "link": "https://youtu.be/AC1Wz7hmxlE",
            "percent": 100,
            "hz": 144
        },
        {
            "user": "Zultzz",
            "link": "https://youtu.be/a6bovK1Nl88",
            "percent": 100,
            "hz": 240
        },
        {
            "user": "C4elan",
            "link": "https://youtu.be/4JqofOwpXnI",
            "percent": 100,
            "hz": 240
        },
        {
            "user": "natertot",
            "link": "https://youtu.be/3qjVXJF3OQ0",
            "percent": 100,
            "hz": 240
        },
        {
            "user": "Customize45",
            "link": "https://youtu.be/X4Zu2r-n-EY",
            "percent": 100,
            "hz": 288
        },
        {
            "user": "Artaix",
            "link": "https://youtu.be/wqkwPwTyTQI",
            "percent": 100,
            "hz": 144
        },
        {
            "user": "Perikite",
            "link": "https://youtu.be/hav4OS70gsE",
            "percent": 100,
            "hz": 240
        },
        {
            "user": "LilTerry",
            "link": "https://www.youtube.com/watch?v=Fxpm4Ob8hCk",
            "percent": 100,
            "hz": 240
        },
        {
            "user": "Shadz",
            "link": "https://youtu.be/xP7W8Q9HIyw",
            "percent": 100,
            "hz": 360
        },
        {
            "user": "Shira",
            "link": "https://youtu.be/4VQBGPHZIVo",
            "percent": 100,
            "hz": 240
        },
        {
            "user": "nCorr",
            "link": "https://www.youtube.com/watch?v=HD-Z1UjwMrM&t=14s",
            "percent": 100,
            "hz": 240
        },
        {
            "user": "Breakthrough",
            "link": "https://www.youtube.com/watch?v=QU6fgoD30RY",
            "percent": 100,
            "hz": 360
        },
        {
            "user": "Al3G",
            "link": "",
            "percent": 100,
            "hz": 240
        },
        {
            "user": "Stainsley",
            "link": "https://www.youtube.com/watch?v=Epve5XEN2l8",
            "percent": 100,
            "hz": 240
        },
        {
            "user": "woolfys",
            "link": "https://www.youtube.com/watch?v=HEE6tgVyWck",
            "percent": 100,
            "hz": 240
        },
        {
            "user": "Blayne",
            "link": "https://www.youtube.com/watch?v=zFoxShH_rD0",
            "percent": 100,
            "hz": 360
        },
        {
            "user": "Beanus",
            "link": "https://www.youtube.com/watch?v=-oDFsznmmqI&t=13s",
            "percent": 100,
            "hz": "(CBF) 9999"
        },
        {
            "user": "Darthskril",
            "link": "https://www.youtube.com/watch?v=SON5FZAKP9E",
            "percent": 100,
            "hz": 144
        },
        {
            "user": "kate",
            "link": "https://www.youtube.com/watch?v=pn1aguJS7aY",
            "percent": 100,
            "hz": "(CBF) 240"
        }        
    ]
}
